monthify/__init__.py
monthify/__main__.py
monthify/args.py
monthify/auth.py
monthify/config.py
monthify/main.py
monthify/playlist.py
monthify/protocols.py
monthify/script.py
monthify/track.py
monthify/utils.py
monthify-0.6.1.dist-info/METADATA
monthify-0.6.1.dist-info/WHEEL
monthify-0.6.1.dist-info/entry_points.txt
monthify-0.6.1.dist-info/RECORD
