Metadata-Version: 2.4
Name: monthify
Version: 0.6.1
Summary: Sorts liked spotify tracks into playlists by the month they were liked.
Author-email: Madiba Hudson-Quansah <mhquansah@gmail.com>
Requires-Python: >=3.11
Requires-Dist: appdirs<2,>=1.4.4
Requires-Dist: cachetools<6,>=5.2.1
Requires-Dist: loguru<0.7,>=0.6.0
Requires-Dist: mutagen<2,>=1.47.0
Requires-Dist: pathvalidate<4,>=3.2.3
Requires-Dist: rich<14,>=13.1.0
Requires-Dist: spotipy<3,>=2.22.0
Requires-Dist: toml<0.11,>=0.10.2
